stix_shifter_modules/qradar/__init__.py
stix_shifter_modules/qradar/entry_point.py
stix_shifter_modules/qradar/configuration/config.json
stix_shifter_modules/qradar/configuration/dialects.json
stix_shifter_modules/qradar/configuration/lang_en.json
stix_shifter_modules/qradar/stix_translation/__init__.py
stix_shifter_modules/qradar/stix_translation/aql_query_translator.py
stix_shifter_modules/qradar/stix_translation/json_to_stix_translator.py
stix_shifter_modules/qradar/stix_translation/query_constructor.py
stix_shifter_modules/qradar/stix_translation/query_translator.py
stix_shifter_modules/qradar/stix_translation/transformers.py
stix_shifter_modules/qradar/stix_translation/json/aql_events_fields.json
stix_shifter_modules/qradar/stix_translation/json/aql_flows_fields.json
stix_shifter_modules/qradar/stix_translation/json/events_from_stix_map.json
stix_shifter_modules/qradar/stix_translation/json/flows_from_stix_map.json
stix_shifter_modules/qradar/stix_translation/json/network_protocol_map.json
stix_shifter_modules/qradar/stix_translation/json/operators.json
stix_shifter_modules/qradar/stix_translation/json/to_stix_map.json
stix_shifter_modules/qradar/stix_translation/json/stix_2_1/events_from_stix_map.json
stix_shifter_modules/qradar/stix_translation/json/stix_2_1/flows_from_stix_map.json
stix_shifter_modules/qradar/stix_translation/json/stix_2_1/to_stix_map.json
stix_shifter_modules/qradar/stix_transmission/__init__.py
stix_shifter_modules/qradar/stix_transmission/api_client.py
stix_shifter_modules/qradar/stix_transmission/delete_connector.py
stix_shifter_modules/qradar/stix_transmission/error_mapper.py
stix_shifter_modules/qradar/stix_transmission/ping_connector.py
stix_shifter_modules/qradar/stix_transmission/query_connector.py
stix_shifter_modules/qradar/stix_transmission/results_connector.py
stix_shifter_modules/qradar/stix_transmission/status_connector.py
stix_shifter_modules_qradar-8.0.2.dist-info/licenses/AUTHORS.md
stix_shifter_modules_qradar-8.0.2.dist-info/licenses/LICENSE.md
stix_shifter_modules_qradar-8.0.2.dist-info/licenses/NOTICE
stix_shifter_modules_qradar-8.0.2.dist-info/METADATA
stix_shifter_modules_qradar-8.0.2.dist-info/WHEEL
stix_shifter_modules_qradar-8.0.2.dist-info/top_level.txt
stix_shifter_modules_qradar-8.0.2.dist-info/RECORD
